lineales/__init__.py
lineales/cramer.py
lineales/gauss.py
lineales/gauss_jordan.py
lineales/gauss_seidel.py
lineales/jacobi.py
lineales/lu.py
no_lineales/__init__.py
no_lineales/biseccion.py
mj21013uno-0.1.0.dist-info/METADATA
mj21013uno-0.1.0.dist-info/WHEEL
mj21013uno-0.1.0.dist-info/top_level.txt
mj21013uno-0.1.0.dist-info/RECORD
